{
  "0": "analysis.ts",
  "1": "RemixStudio.tsx",
  "2": "route.ts",
  "3": "ffmpeg-core.js",
  "4": "server.js",
  "5": "TunebadApp",
  "6": "layout.tsx",
  "7": "rate-limit.ts",
  "8": "dependencies",
  "9": "lufs.ts",
  "10": "VideoTool.tsx",
  "11": "link-analysis.ts",
  "12": "AnalyzerPanel.tsx",
  "13": "ToolFaq.tsx",
  "14": "CutterPanel.tsx",
  "15": "ToolPageShell.tsx",
  "16": "backends.ts",
  "17": "AudioMasteringTool.tsx",
  "18": "compilerOptions",
  "19": "seed-songs.mjs",
  "20": "VideoTool.tsx",
  "21": "fs",
  "22": "LoudnessPanel.tsx",
  "23": "VideoTool.tsx",
  "24": "page.tsx",
  "26": "getWasmTableEntry",
  "27": "getSocketFromFD",
  "28": "CutterPanel.tsx",
  "29": "ExceptionInfo",
  "30": "intArrayFromString",
  "31": "ReverbEq.tsx",
  "32": "AnalysisResult",
  "33": "_strftime",
  "35": "asyncLoad",
  "36": "abort",
  "37": "audio-joiner.ts",
  "38": "manifest.json",
  "39": "page.tsx",
  "40": "setup-ytdlp.mjs",
  "42": "callRuntimeCallbacks",
  "43": "tunebad-bridge.sh",
  "44": "TuneBad — Security Review",
  "45": "TuneBad",
  "46": "LoudnessPanel.tsx",
  "47": "getEnvStrings",
  "48": "next.config.mjs",
  "49": "gen-og-files.mjs",
  "50": "TuneBad remote downloader",
  "51": "essentia.d.ts",
  "52": "next-env.d.ts",
  "53": "downloadBlob",
  "54": "tunebad-local.sh",
  "55": "vendor-ffmpeg.mjs",
  "57": "route.ts",
  "58": "LandingSeo.tsx",
  "59": "useHistory.ts",
  "60": "page.tsx",
  "61": "MetronomeCard.tsx",
  "62": "usePlaylistBatch.ts",
  "63": "media-url.ts",
  "64": "format.ts",
  "65": "MetronomeCard.tsx",
  "67": "constants.ts",
  "68": "page.tsx",
  "69": "youtube-playlist.ts",
  "70": "page.tsx",
  "71": "delay.ts",
  "72": "page.tsx",
  "73": "page.tsx",
  "74": "page.tsx",
  "75": "page.tsx",
  "76": "page.tsx",
  "77": "NightcoreTool.tsx",
  "78": "artists.ts",
  "79": "AnalyzerPanel",
  "80": "audio-joiner.ts"
}
